ProjectB_clientside_template_package/MainController.py
ProjectB_clientside_template_package/ClientSocketControl/DataStructure.py
ProjectB_clientside_template_package/ClientSocketControl/SocketClient.py
ProjectB_clientside_template_package/Indicators/BollingerBands.py
ProjectB_clientside_template_package/TradeControl/Order.py
ProjectB_clientside_template_package/TradeControl/Profile.py
ProjectB_clientside_template_package/TradeControl/TradeController.py
ProjectB_clientside_template_package/TradeControl/OrderActionConstants/Action.py
ProjectB_clientside_template_package/TradeControl/OrderActionConstants/Direction.py
ProjectB_clientside_template_package/TradeControl/OrderActionConstants/ExpiryDate.py
ProjectB_clientside_template_package/TradeControl/OrderActionConstants/StrikePrice.py
ProjectB_clientside_template_package-1.3.dist-info/METADATA
ProjectB_clientside_template_package-1.3.dist-info/WHEEL
ProjectB_clientside_template_package-1.3.dist-info/top_level.txt
ProjectB_clientside_template_package-1.3.dist-info/RECORD
